afromessage/__init__.py
afromessage/client.py
afromessage/otp.py
afromessage/sms.py
afromessage/utils.py
afromessage/models/__init__.py
afromessage/models/otp_models.py
afromessage/models/sms_models.py
afromessage-0.1.4.dist-info/licenses/LICENSE
afromessage-0.1.4.dist-info/METADATA
afromessage-0.1.4.dist-info/WHEEL
afromessage-0.1.4.dist-info/entry_points.txt
afromessage-0.1.4.dist-info/top_level.txt
afromessage-0.1.4.dist-info/RECORD
